sjSDM_py/__init__.py
sjSDM_py/dist_mvp.py
sjSDM_py/model_LVM.py
sjSDM_py/model_sjSDM.py
sjSDM_py/model_svi.py
sjSDM_py/optimizer.py
sjSDM_py/utils_fa.py
tests/__init__.py
tests/test_model_LVM.py
tests/test_sjSDM.py
sjSDM_py-0.1.1.dist-info/LICENSE
sjSDM_py-0.1.1.dist-info/METADATA
sjSDM_py-0.1.1.dist-info/WHEEL
sjSDM_py-0.1.1.dist-info/top_level.txt
sjSDM_py-0.1.1.dist-info/RECORD
