Metadata-Version: 2.1
Name: sjSDM-py
Version: 0.1.1
Summary: jSDM package
Home-page: https://github.com/TheoreticalEcology/s-jSDM
Author: Maximilian Pichler
Author-email: Maximilian.Pichler@ur.de
License: UNKNOWN
Platform: UNKNOWN
Classifier: License :: OSI Approved :: GNU General Public License v3 (GPLv3)
Classifier: Operating System :: OS Independent
Classifier: Programming Language :: Python :: 3
Classifier: Programming Language :: Python :: 3.6
Classifier: Programming Language :: Python :: 3.7
Classifier: Programming Language :: Python :: 3.8
Requires-Dist: numpy
